[{"ime":"Angela","grad":"Skopje","prosek":9.9},{"ime":"Marko","grad":"Ohrid","prosek":9.8},{"ime":"Angela","grad":"Skopje","prosek":9.7},{"ime":"Jasmina","grad":"Kicevo","prosek":9.7},{"ime":"Jasmina","grad":"Kicevo","prosek":9.7},{"ime":"Jasmina","grad":"Kicevo","prosek":9.7},{"ime":"Elena","grad":"Kicevo","prosek":9.7},{"ime":"Kate","grad":"Skopje","prosek":9.7},{"ime":"Elena","grad":"Gevgelija","prosek":9.2},{"ime":"Elena","grad":"Gevgelija","prosek":9.2},{"ime":"Marija","grad":"Ohrid","prosek":9.2},{"ime":"Oliver","grad":"Ohrid","prosek":9.3}]